addressbookvad/__init__.py
addressbookvad/main.py
addressbookvad-1.2.0.dist-info/LICENSE
addressbookvad-1.2.0.dist-info/METADATA
addressbookvad-1.2.0.dist-info/WHEEL
addressbookvad-1.2.0.dist-info/entry_points.txt
addressbookvad-1.2.0.dist-info/top_level.txt
addressbookvad-1.2.0.dist-info/RECORD
